directorfile/__init__.py
directorfile/common.py
directorfile/projector.py
directorfile/archive/__init__.py
directorfile/archive/application.py
directorfile/archive/base.py
directorfile/archive/director.py
directorfile/archive/shockwave.py
directorfile-0.0.1.dist-info/LICENSE
directorfile-0.0.1.dist-info/METADATA
directorfile-0.0.1.dist-info/WHEEL
directorfile-0.0.1.dist-info/top_level.txt
directorfile-0.0.1.dist-info/RECORD
