Metadata-Version: 2.1
Name: directorfile
Version: 0.0.1
Summary: A python module to read and manipulate Macromedia/Adobe Director files
Home-page: https://github.com/Prilkop/directorfile
Author: Adam Rimon
Author-email: 
License: MIT License
Classifier: Development Status :: 2 - Pre-Alpha
Classifier: Intended Audience :: Developers
Classifier: Programming Language :: Python
Classifier: Topic :: File Formats
Classifier: Topic :: Utilities
Classifier: License :: OSI Approved :: MIT License
Classifier: Operating System :: OS Independent
License-File: LICENSE
